{
	"info": {
		"_postman_id": "40810e5e-2eef-40ab-89ed-6a0138489cf7",
		"name": "barbershop-api Copy",
		"description": "The API for barbershop project",
		"schema": "https://schema.getpostman.com/json/collection/v2.1.0/collection.json",
		"_exporter_id": "28284845"
	},
	"item": [
		{
			"name": "auth",
			"item": [
				{
					"name": "register",
					"item": [
						{
							"name": "To create new user",
							"event": [
								{
									"listen": "prerequest",
									"script": {
										"exec": [
											"pm.environment.set(\"name\", pm.variables.replaceIn(\"{{$randomFullName}}\"));\r",
											"pm.environment.set(\"email\", pm.variables.replaceIn(\"{{$randomEmail}}\"));\r",
											"pm.environment.set(\"number\", pm.variables.replaceIn(\"{{$randomPhoneNumber}}\"));\r",
											"pm.environment.set(\"password\", pm.variables.replaceIn(\"{{$randomPassword}}\"));\r",
											"pm.environment.set(\"photo_url\", pm.variables.replaceIn(\"{{$randomAvatarImage}}\"));"
										],
										"type": "text/javascript"
									}
								},
								{
									"listen": "test",
									"script": {
										"exec": [
											"pm.test(\"Successful POST request\", function () {\r",
											"    pm.expect(pm.response.code).to.be.oneOf([201, 202]);\r",
											"});\r",
											"pm.test(\"Response time is less than 200ms\", function () {\r",
											"    pm.expect(pm.response.responseTime).to.be.below(200);\r",
											"});\r",
											"pm.collectionVariables.set(\"id_user\", pm.response.json().data.id);"
										],
										"type": "text/javascript"
									}
								}
							],
							"request": {
								"method": "POST",
								"header": [
									{
										"key": "Content-Type",
										"value": "application/json"
									},
									{
										"key": "Accept",
										"value": "application/json"
									}
								],
								"body": {
									"mode": "raw",
									"raw": "{\n  \"email\": \"{{email}}\",\n  \"password\": \"{{password}}\",\n  \"name\": \"{{name}}\",\n  \"photo_url\": \"{{photo_url}}\",\n  \"number\": \"{{number}}\",\n  \"role\": \"Admin\"\n}",
									"options": {
										"raw": {
											"headerFamily": "json",
											"language": "json"
										}
									}
								},
								"url": {
									"raw": "{{baseUrl}}/api/auth/register",
									"host": [
										"{{baseUrl}}"
									],
									"path": [
										"api",
										"auth",
										"register"
									]
								},
								"description": "To create new user"
							},
							"response": [
								{
									"name": "To create new user",
									"originalRequest": {
										"method": "POST",
										"header": [
											{
												"key": "Content-Type",
												"value": "application/json"
											},
											{
												"key": "Accept",
												"value": "application/json"
											}
										],
										"body": {
											"mode": "raw",
											"raw": "{\n  \"email\": \"{{email}}\",\n  \"password\": \"{{password}}\",\n  \"name\": \"{{name}}\",\n  \"photo_url\": \"{{photo_url}}\",\n  \"number\": \"{{number}}\",\n  \"role\": \"Customer\"\n}",
											"options": {
												"raw": {
													"headerFamily": "json",
													"language": "json"
												}
											}
										},
										"url": {
											"raw": "{{baseUrl}}/api/auth/register",
											"host": [
												"{{baseUrl}}"
											],
											"path": [
												"api",
												"auth",
												"register"
											]
										}
									},
									"status": "Bad Request",
									"code": 400,
									"_postman_previewlanguage": "json",
									"header": [
										{
											"key": "X-Powered-By",
											"value": "Express"
										},
										{
											"key": "Content-Type",
											"value": "application/json; charset=utf-8"
										},
										{
											"key": "Content-Length",
											"value": "45"
										},
										{
											"key": "ETag",
											"value": "W/\"2d-O9+xirTktDEF8echUYAvAly7wUk\""
										},
										{
											"key": "Date",
											"value": "Sun, 10 Dec 2023 21:48:19 GMT"
										},
										{
											"key": "Connection",
											"value": "keep-alive"
										},
										{
											"key": "Keep-Alive",
											"value": "timeout=5"
										}
									],
									"cookie": [],
									"body": "{\n    \"code\": 400,\n    \"message\": \"email must be unique\"\n}"
								},
								{
									"name": "To create new user",
									"originalRequest": {
										"method": "POST",
										"header": [
											{
												"key": "Content-Type",
												"value": "application/json"
											},
											{
												"key": "Accept",
												"value": "application/json"
											}
										],
										"body": {
											"mode": "raw",
											"raw": "{\n  \"email\": \"{{email}}\",\n  \"password\": \"{{password}}\",\n  \"name\": \"{{name}}\",\n  \"photo_url\": \"{{photo_url}}\",\n  \"number\": \"{{number}}\",\n  \"role\": \"Customer\"\n}",
											"options": {
												"raw": {
													"headerFamily": "json",
													"language": "json"
												}
											}
										},
										"url": {
											"raw": "{{baseUrl}}/api/auth/register",
											"host": [
												"{{baseUrl}}"
											],
											"path": [
												"api",
												"auth",
												"register"
											]
										}
									},
									"status": "Created",
									"code": 201,
									"_postman_previewlanguage": "json",
									"header": [
										{
											"key": "X-Powered-By",
											"value": "Express"
										},
										{
											"key": "Content-Type",
											"value": "application/json; charset=utf-8"
										},
										{
											"key": "Content-Length",
											"value": "51"
										},
										{
											"key": "ETag",
											"value": "W/\"33-7yopKOrtik7mvFINugPo3PY+wlw\""
										},
										{
											"key": "Date",
											"value": "Sun, 10 Dec 2023 21:50:00 GMT"
										},
										{
											"key": "Connection",
											"value": "keep-alive"
										},
										{
											"key": "Keep-Alive",
											"value": "timeout=5"
										}
									],
									"cookie": [],
									"body": "{\n    \"code\": 201,\n    \"message\": \"User successfully created.\"\n}"
								}
							]
						}
					]
				},
				{
					"name": "To Login in application",
					"event": [
						{
							"listen": "test",
							"script": {
								"exec": [
									"pm.test(\"Status code is 200\", function () {\r",
									"    pm.response.to.have.status(200);\r",
									"});\r",
									"pm.test(\"Response time is less than 200ms\", function () {\r",
									"    pm.expect(pm.response.responseTime).to.be.below(200);\r",
									"});\r",
									"pm.collectionVariables.set(\"token_customer\", pm.response.json().data);"
								],
								"type": "text/javascript"
							}
						}
					],
					"request": {
						"method": "POST",
						"header": [
							{
								"key": "Content-Type",
								"value": "application/json"
							},
							{
								"key": "Accept",
								"value": "application/json"
							}
						],
						"body": {
							"mode": "raw",
							"raw": "{\n  \"email\": \"{{email}}\",\n  \"password\": \"{{password}}\"\n}",
							"options": {
								"raw": {
									"headerFamily": "json",
									"language": "json"
								}
							}
						},
						"url": {
							"raw": "{{baseUrl}}/api/auth",
							"host": [
								"{{baseUrl}}"
							],
							"path": [
								"api",
								"auth"
							]
						},
						"description": "To Login in application"
					},
					"response": [
						{
							"name": "To Login in application",
							"originalRequest": {
								"method": "POST",
								"header": [
									{
										"key": "Content-Type",
										"value": "application/json"
									},
									{
										"key": "Accept",
										"value": "application/json"
									}
								],
								"body": {
									"mode": "raw",
									"raw": "{\n  \"email\": \"{{email}}\",\n  \"password\": \"{{password}}\"\n}",
									"options": {
										"raw": {
											"headerFamily": "json",
											"language": "json"
										}
									}
								},
								"url": {
									"raw": "{{baseUrl}}/api/auth",
									"host": [
										"{{baseUrl}}"
									],
									"path": [
										"api",
										"auth"
									]
								}
							},
							"status": "OK",
							"code": 200,
							"_postman_previewlanguage": "json",
							"header": [
								{
									"key": "X-Powered-By",
									"value": "Express"
								},
								{
									"key": "Set-Cookie",
									"value": "token=Bearer%20eyJhbGciOiJIUzI1NiIsInR5cCI6IkpXVCJ9.eyJpZCI6NiwiZW1haWwiOiJ2b2Nhc2lhQGdtYWlsLmNvLmlkIiwiaWF0IjoxNzAyMjQ1NDE0LCJleHAiOjE3MDIzMzE4MTR9.pz0bYNdxp3fDdcdj0nquotoRMXIG_OD6DO-EGWu7Ntw; Max-Age=3600; Path=/; Expires=Sun, 10 Dec 2023 22:56:54 GMT; HttpOnly"
								},
								{
									"key": "Content-Type",
									"value": "application/json; charset=utf-8"
								},
								{
									"key": "Content-Length",
									"value": "226"
								},
								{
									"key": "ETag",
									"value": "W/\"e2-oEcbhB5Sf/uRS4zlsfLzCe5W3xA\""
								},
								{
									"key": "Date",
									"value": "Sun, 10 Dec 2023 21:56:54 GMT"
								},
								{
									"key": "Connection",
									"value": "keep-alive"
								},
								{
									"key": "Keep-Alive",
									"value": "timeout=5"
								}
							],
							"cookie": [],
							"body": "{\n    \"code\": 200,\n    \"data\": \"eyJhbGciOiJIUzI1NiIsInR5cCI6IkpXVCJ9.eyJpZCI6NiwiZW1haWwiOiJ2b2Nhc2lhQGdtYWlsLmNvLmlkIiwiaWF0IjoxNzAyMjQ1NDE0LCJleHAiOjE3MDIzMzE4MTR9.pz0bYNdxp3fDdcdj0nquotoRMXIG_OD6DO-EGWu7Ntw\",\n    \"message\": \"Login success.\"\n}"
						},
						{
							"name": "To Login in application",
							"originalRequest": {
								"method": "POST",
								"header": [
									{
										"key": "Content-Type",
										"value": "application/json"
									},
									{
										"key": "Accept",
										"value": "application/json"
									}
								],
								"body": {
									"mode": "raw",
									"raw": "{\n  \"emaifl\": \"{{email}}\",\n  \"password\": \"{{password}}\"\n}",
									"options": {
										"raw": {
											"headerFamily": "json",
											"language": "json"
										}
									}
								},
								"url": {
									"raw": "{{baseUrl}}/api/auth",
									"host": [
										"{{baseUrl}}"
									],
									"path": [
										"api",
										"auth"
									]
								}
							},
							"status": "Bad Request",
							"code": 400,
							"_postman_previewlanguage": "json",
							"header": [
								{
									"key": "X-Powered-By",
									"value": "Express"
								},
								{
									"key": "Content-Type",
									"value": "application/json; charset=utf-8"
								},
								{
									"key": "Content-Length",
									"value": "42"
								},
								{
									"key": "ETag",
									"value": "W/\"2a-jhZ7jVCP5dGc7fU3Fk9BAweLsTI\""
								},
								{
									"key": "Date",
									"value": "Sun, 10 Dec 2023 21:57:19 GMT"
								},
								{
									"key": "Connection",
									"value": "keep-alive"
								},
								{
									"key": "Keep-Alive",
									"value": "timeout=5"
								}
							],
							"cookie": [],
							"body": "{\n    \"code\": 400,\n    \"message\": \"Email harus diisi\"\n}"
						},
						{
							"name": "To Login in application",
							"originalRequest": {
								"method": "POST",
								"header": [
									{
										"key": "Content-Type",
										"value": "application/json"
									},
									{
										"key": "Accept",
										"value": "application/json"
									}
								],
								"body": {
									"mode": "raw",
									"raw": "{\n  \"email\": \"{{email}}\",\n  \"password\": \"{{password}sds}\"\n}",
									"options": {
										"raw": {
											"headerFamily": "json",
											"language": "json"
										}
									}
								},
								"url": {
									"raw": "{{baseUrl}}/api/auth",
									"host": [
										"{{baseUrl}}"
									],
									"path": [
										"api",
										"auth"
									]
								}
							},
							"status": "Unauthorized",
							"code": 401,
							"_postman_previewlanguage": "json",
							"header": [
								{
									"key": "X-Powered-By",
									"value": "Express"
								},
								{
									"key": "Content-Type",
									"value": "application/json; charset=utf-8"
								},
								{
									"key": "Content-Length",
									"value": "50"
								},
								{
									"key": "ETag",
									"value": "W/\"32-gM+vI0FygCwM+jxBWO0l6L1X4Y0\""
								},
								{
									"key": "Date",
									"value": "Sun, 10 Dec 2023 22:02:30 GMT"
								},
								{
									"key": "Connection",
									"value": "keep-alive"
								},
								{
									"key": "Keep-Alive",
									"value": "timeout=5"
								}
							],
							"cookie": [],
							"body": "{\n    \"code\": 401,\n    \"message\": \"Invalid email or password\"\n}"
						},
						{
							"name": "To Login in application",
							"originalRequest": {
								"method": "POST",
								"header": [
									{
										"key": "Content-Type",
										"value": "application/json"
									},
									{
										"key": "Accept",
										"value": "application/json"
									}
								],
								"body": {
									"mode": "raw",
									"raw": "{\n  \"email\": \"{{email}}\",\n  \"password\": \"{{password}}\"\n}",
									"options": {
										"raw": {
											"headerFamily": "json",
											"language": "json"
										}
									}
								},
								"url": {
									"raw": "{{baseUrl}}/api/auth",
									"host": [
										"{{baseUrl}}"
									],
									"path": [
										"api",
										"auth"
									]
								}
							},
							"status": "OK",
							"code": 200,
							"_postman_previewlanguage": "json",
							"header": [
								{
									"key": "X-Powered-By",
									"value": "Express"
								},
								{
									"key": "Set-Cookie",
									"value": "access-token=Bearer%20eyJhbGciOiJIUzI1NiIsInR5cCI6IkpXVCJ9.eyJpZCI6MSwiZW1haWwiOiJjdXN0b21lckBtYWlsLmNvbSIsImlhdCI6MTcwMjQ3MzQ2MiwiZXhwIjoxNzAyNTU5ODYyfQ.9EBjfto9-EVSYMtHIIMfQKFNePsIayQpFLk-7qZ-j8I; Max-Age=3600; Path=/; Expires=Wed, 13 Dec 2023 14:17:42 GMT; HttpOnly"
								},
								{
									"key": "Content-Type",
									"value": "application/json; charset=utf-8"
								},
								{
									"key": "Content-Length",
									"value": "224"
								},
								{
									"key": "ETag",
									"value": "W/\"e0-lmXaV43x73mfDfhei6e6RmVgrkQ\""
								},
								{
									"key": "Date",
									"value": "Wed, 13 Dec 2023 13:17:42 GMT"
								},
								{
									"key": "Connection",
									"value": "keep-alive"
								},
								{
									"key": "Keep-Alive",
									"value": "timeout=5"
								}
							],
							"cookie": [],
							"body": "{\n    \"code\": 200,\n    \"data\": \"eyJhbGciOiJIUzI1NiIsInR5cCI6IkpXVCJ9.eyJpZCI6MSwiZW1haWwiOiJjdXN0b21lckBtYWlsLmNvbSIsImlhdCI6MTcwMjQ3MzQ2MiwiZXhwIjoxNzAyNTU5ODYyfQ.9EBjfto9-EVSYMtHIIMfQKFNePsIayQpFLk-7qZ-j8I\",\n    \"message\": \"Login success.\"\n}"
						}
					]
				},
				{
					"name": "To Login in application Admin",
					"event": [
						{
							"listen": "test",
							"script": {
								"exec": [
									"pm.test(\"Status code is 200\", function () {\r",
									"    pm.response.to.have.status(200);\r",
									"});\r",
									"pm.test(\"Response time is less than 200ms\", function () {\r",
									"    pm.expect(pm.response.responseTime).to.be.below(200);\r",
									"});\r",
									"pm.collectionVariables.set(\"token_admin\", pm.response.json().data);"
								],
								"type": "text/javascript"
							}
						}
					],
					"request": {
						"method": "POST",
						"header": [
							{
								"key": "Content-Type",
								"value": "application/json"
							},
							{
								"key": "Accept",
								"value": "application/json"
							}
						],
						"body": {
							"mode": "raw",
							"raw": "{\n  \"email\": \"{{admin_email}}\",\n  \"password\": \"{{admin_password}}\"\n}",
							"options": {
								"raw": {
									"headerFamily": "json",
									"language": "json"
								}
							}
						},
						"url": {
							"raw": "{{baseUrl}}/api/auth",
							"host": [
								"{{baseUrl}}"
							],
							"path": [
								"api",
								"auth"
							]
						},
						"description": "To Login in application"
					},
					"response": [
						{
							"name": "To Login in application",
							"originalRequest": {
								"method": "POST",
								"header": [
									{
										"key": "Content-Type",
										"value": "application/json"
									},
									{
										"key": "Accept",
										"value": "application/json"
									}
								],
								"body": {
									"mode": "raw",
									"raw": "{\n  \"email\": \"{{email}}\",\n  \"password\": \"{{password}}\"\n}",
									"options": {
										"raw": {
											"headerFamily": "json",
											"language": "json"
										}
									}
								},
								"url": {
									"raw": "{{baseUrl}}/api/auth",
									"host": [
										"{{baseUrl}}"
									],
									"path": [
										"api",
										"auth"
									]
								}
							},
							"status": "OK",
							"code": 200,
							"_postman_previewlanguage": "json",
							"header": [
								{
									"key": "X-Powered-By",
									"value": "Express"
								},
								{
									"key": "Set-Cookie",
									"value": "token=Bearer%20eyJhbGciOiJIUzI1NiIsInR5cCI6IkpXVCJ9.eyJpZCI6NiwiZW1haWwiOiJ2b2Nhc2lhQGdtYWlsLmNvLmlkIiwiaWF0IjoxNzAyMjQ1NDE0LCJleHAiOjE3MDIzMzE4MTR9.pz0bYNdxp3fDdcdj0nquotoRMXIG_OD6DO-EGWu7Ntw; Max-Age=3600; Path=/; Expires=Sun, 10 Dec 2023 22:56:54 GMT; HttpOnly"
								},
								{
									"key": "Content-Type",
									"value": "application/json; charset=utf-8"
								},
								{
									"key": "Content-Length",
									"value": "226"
								},
								{
									"key": "ETag",
									"value": "W/\"e2-oEcbhB5Sf/uRS4zlsfLzCe5W3xA\""
								},
								{
									"key": "Date",
									"value": "Sun, 10 Dec 2023 21:56:54 GMT"
								},
								{
									"key": "Connection",
									"value": "keep-alive"
								},
								{
									"key": "Keep-Alive",
									"value": "timeout=5"
								}
							],
							"cookie": [],
							"body": "{\n    \"code\": 200,\n    \"data\": \"eyJhbGciOiJIUzI1NiIsInR5cCI6IkpXVCJ9.eyJpZCI6NiwiZW1haWwiOiJ2b2Nhc2lhQGdtYWlsLmNvLmlkIiwiaWF0IjoxNzAyMjQ1NDE0LCJleHAiOjE3MDIzMzE4MTR9.pz0bYNdxp3fDdcdj0nquotoRMXIG_OD6DO-EGWu7Ntw\",\n    \"message\": \"Login success.\"\n}"
						},
						{
							"name": "To Login in application",
							"originalRequest": {
								"method": "POST",
								"header": [
									{
										"key": "Content-Type",
										"value": "application/json"
									},
									{
										"key": "Accept",
										"value": "application/json"
									}
								],
								"body": {
									"mode": "raw",
									"raw": "{\n  \"emaifl\": \"{{email}}\",\n  \"password\": \"{{password}}\"\n}",
									"options": {
										"raw": {
											"headerFamily": "json",
											"language": "json"
										}
									}
								},
								"url": {
									"raw": "{{baseUrl}}/api/auth",
									"host": [
										"{{baseUrl}}"
									],
									"path": [
										"api",
										"auth"
									]
								}
							},
							"status": "Bad Request",
							"code": 400,
							"_postman_previewlanguage": "json",
							"header": [
								{
									"key": "X-Powered-By",
									"value": "Express"
								},
								{
									"key": "Content-Type",
									"value": "application/json; charset=utf-8"
								},
								{
									"key": "Content-Length",
									"value": "42"
								},
								{
									"key": "ETag",
									"value": "W/\"2a-jhZ7jVCP5dGc7fU3Fk9BAweLsTI\""
								},
								{
									"key": "Date",
									"value": "Sun, 10 Dec 2023 21:57:19 GMT"
								},
								{
									"key": "Connection",
									"value": "keep-alive"
								},
								{
									"key": "Keep-Alive",
									"value": "timeout=5"
								}
							],
							"cookie": [],
							"body": "{\n    \"code\": 400,\n    \"message\": \"Email harus diisi\"\n}"
						},
						{
							"name": "To Login in application",
							"originalRequest": {
								"method": "POST",
								"header": [
									{
										"key": "Content-Type",
										"value": "application/json"
									},
									{
										"key": "Accept",
										"value": "application/json"
									}
								],
								"body": {
									"mode": "raw",
									"raw": "{\n  \"email\": \"{{email}}\",\n  \"password\": \"{{password}sds}\"\n}",
									"options": {
										"raw": {
											"headerFamily": "json",
											"language": "json"
										}
									}
								},
								"url": {
									"raw": "{{baseUrl}}/api/auth",
									"host": [
										"{{baseUrl}}"
									],
									"path": [
										"api",
										"auth"
									]
								}
							},
							"status": "Unauthorized",
							"code": 401,
							"_postman_previewlanguage": "json",
							"header": [
								{
									"key": "X-Powered-By",
									"value": "Express"
								},
								{
									"key": "Content-Type",
									"value": "application/json; charset=utf-8"
								},
								{
									"key": "Content-Length",
									"value": "50"
								},
								{
									"key": "ETag",
									"value": "W/\"32-gM+vI0FygCwM+jxBWO0l6L1X4Y0\""
								},
								{
									"key": "Date",
									"value": "Sun, 10 Dec 2023 22:02:30 GMT"
								},
								{
									"key": "Connection",
									"value": "keep-alive"
								},
								{
									"key": "Keep-Alive",
									"value": "timeout=5"
								}
							],
							"cookie": [],
							"body": "{\n    \"code\": 401,\n    \"message\": \"Invalid email or password\"\n}"
						},
						{
							"name": "To Login in application Admin",
							"originalRequest": {
								"method": "POST",
								"header": [
									{
										"key": "Content-Type",
										"value": "application/json"
									},
									{
										"key": "Accept",
										"value": "application/json"
									}
								],
								"body": {
									"mode": "raw",
									"raw": "{\n  \"email\": \"{{admin_email}}\",\n  \"password\": \"{{password}}\"\n}",
									"options": {
										"raw": {
											"headerFamily": "json",
											"language": "json"
										}
									}
								},
								"url": {
									"raw": "{{baseUrl}}/api/auth",
									"host": [
										"{{baseUrl}}"
									],
									"path": [
										"api",
										"auth"
									]
								}
							},
							"status": "Unauthorized",
							"code": 401,
							"_postman_previewlanguage": "json",
							"header": [
								{
									"key": "X-Powered-By",
									"value": "Express"
								},
								{
									"key": "Content-Type",
									"value": "application/json; charset=utf-8"
								},
								{
									"key": "Content-Length",
									"value": "50"
								},
								{
									"key": "ETag",
									"value": "W/\"32-gM+vI0FygCwM+jxBWO0l6L1X4Y0\""
								},
								{
									"key": "Date",
									"value": "Wed, 13 Dec 2023 16:18:24 GMT"
								},
								{
									"key": "Connection",
									"value": "keep-alive"
								},
								{
									"key": "Keep-Alive",
									"value": "timeout=5"
								}
							],
							"cookie": [],
							"body": "{\n    \"code\": 401,\n    \"message\": \"Invalid email or password\"\n}"
						}
					]
				}
			]
		},
		{
			"name": "user",
			"item": [
				{
					"name": "{id}",
					"item": [
						{
							"name": "To fetch user data",
							"event": [
								{
									"listen": "test",
									"script": {
										"exec": [
											"pm.test(\"Status code is 200\", function () {\r",
											"    pm.response.to.have.status(200);\r",
											"});\r",
											"pm.test(\"Response time is less than 200ms\", function () {\r",
											"    pm.expect(pm.response.responseTime).to.be.below(200);\r",
											"});"
										],
										"type": "text/javascript"
									}
								}
							],
							"request": {
								"method": "GET",
								"header": [
									{
										"key": "Accept",
										"value": "application/json"
									}
								],
								"url": {
									"raw": "{{baseUrl}}/api/user",
									"host": [
										"{{baseUrl}}"
									],
									"path": [
										"api",
										"user"
									]
								},
								"description": "To fetch user data"
							},
							"response": [
								{
									"name": "Successfuly get user data",
									"originalRequest": {
										"method": "GET",
										"header": [
											{
												"key": "Accept",
												"value": "application/json"
											}
										],
										"url": {
											"raw": "{{baseUrl}}/user/:id",
											"host": [
												"{{baseUrl}}"
											],
											"path": [
												"user",
												":id"
											],
											"variable": [
												{
													"key": "id"
												}
											]
										}
									},
									"status": "OK",
									"code": 200,
									"_postman_previewlanguage": "json",
									"header": [
										{
											"key": "Content-Type",
											"value": "application/json"
										}
									],
									"cookie": [],
									"body": "{\n  \"id\": \"<number>\",\n  \"name\": \"<string>\",\n  \"passwod\": \"<string>\",\n  \"email\": \"<string>\",\n  \"number\": \"<string>\",\n  \"photo_url\": \"<string>\"\n}"
								},
								{
									"name": "Unauthorized Error",
									"originalRequest": {
										"method": "GET",
										"header": [
											{
												"key": "Accept",
												"value": "application/json"
											}
										],
										"url": {
											"raw": "{{baseUrl}}/user/:id",
											"host": [
												"{{baseUrl}}"
											],
											"path": [
												"user",
												":id"
											],
											"variable": [
												{
													"key": "id"
												}
											]
										}
									},
									"status": "Unauthorized",
									"code": 401,
									"_postman_previewlanguage": "json",
									"header": [
										{
											"key": "Content-Type",
											"value": "application/json"
										}
									],
									"cookie": [],
									"body": "{\n  \"message\": \"<string>\"\n}"
								},
								{
									"name": "To fetch user data",
									"originalRequest": {
										"method": "GET",
										"header": [
											{
												"key": "Accept",
												"value": "application/json"
											}
										],
										"url": {
											"raw": "{{baseUrl}}/api/user/{{id_user}}",
											"host": [
												"{{baseUrl}}"
											],
											"path": [
												"api",
												"user",
												"{{id_user}}"
											]
										}
									},
									"status": "OK",
									"code": 200,
									"_postman_previewlanguage": "json",
									"header": [
										{
											"key": "X-Powered-By",
											"value": "Express"
										},
										{
											"key": "Content-Type",
											"value": "application/json; charset=utf-8"
										},
										{
											"key": "Content-Length",
											"value": "277"
										},
										{
											"key": "ETag",
											"value": "W/\"115-0dHgmzukKr7FybfANMmJVKKZYMg\""
										},
										{
											"key": "Date",
											"value": "Wed, 13 Dec 2023 13:59:29 GMT"
										},
										{
											"key": "Connection",
											"value": "keep-alive"
										},
										{
											"key": "Keep-Alive",
											"value": "timeout=5"
										}
									],
									"cookie": [],
									"body": "{\n    \"code\": 200,\n    \"data\": {\n        \"id\": 1,\n        \"name\": \"vocasia\",\n        \"email\": \"customer@mail.com\",\n        \"number\": \"08122222222\",\n        \"photo_url\": \"https://i.imgur.com/5NvPv4U.png\",\n        \"role\": \"Customer\",\n        \"createdAt\": \"2023-12-10T21:48:07.230Z\",\n        \"updatedAt\": \"2023-12-10T21:48:07.230Z\"\n    },\n    \"message\": \"Data User berhasil diambil\"\n}"
								},
								{
									"name": "To fetch user data",
									"originalRequest": {
										"method": "GET",
										"header": [
											{
												"key": "Accept",
												"value": "application/json"
											}
										],
										"url": {
											"raw": "{{baseUrl}}/api/user/{{id_user}}",
											"host": [
												"{{baseUrl}}"
											],
											"path": [
												"api",
												"user",
												"{{id_user}}"
											]
										}
									},
									"status": "Not Found",
									"code": 404,
									"_postman_previewlanguage": "json",
									"header": [
										{
											"key": "X-Powered-By",
											"value": "Express"
										},
										{
											"key": "Content-Type",
											"value": "application/json; charset=utf-8"
										},
										{
											"key": "Content-Length",
											"value": "39"
										},
										{
											"key": "ETag",
											"value": "W/\"27-FljjMJ0XAHunGVEBxPsq0kubdf4\""
										},
										{
											"key": "Date",
											"value": "Wed, 13 Dec 2023 14:00:07 GMT"
										},
										{
											"key": "Connection",
											"value": "keep-alive"
										},
										{
											"key": "Keep-Alive",
											"value": "timeout=5"
										}
									],
									"cookie": [],
									"body": "{\n    \"code\": 404,\n    \"message\": \"User not found\"\n}"
								}
							]
						},
						{
							"name": "Change User Password",
							"event": [
								{
									"listen": "test",
									"script": {
										"exec": [
											"pm.test(\"Response time is less than 200ms\", function () {\r",
											"    pm.expect(pm.response.responseTime).to.be.below(200);\r",
											"});\r",
											"pm.test(\"Status code is 200\", function () {\r",
											"    pm.response.to.have.status(200);\r",
											"});"
										],
										"type": "text/javascript"
									}
								}
							],
							"request": {
								"method": "PUT",
								"header": [],
								"body": {
									"mode": "raw",
									"raw": "{\r\n    \"old_password\":\"{{admin_password}}\",\r\n    \"new_password\":\"{{admin_password}}\"\r\n}",
									"options": {
										"raw": {
											"language": "json"
										}
									}
								},
								"url": {
									"raw": "{{baseUrl}}/api/user/password",
									"host": [
										"{{baseUrl}}"
									],
									"path": [
										"api",
										"user",
										"password"
									]
								}
							},
							"response": []
						},
						{
							"name": "Change User Role",
							"event": [
								{
									"listen": "test",
									"script": {
										"exec": [
											"pm.test(\"Status code is 200\", function () {\r",
											"    pm.response.to.have.status(200);\r",
											"});\r",
											"pm.test(\"Response time is less than 200ms\", function () {\r",
											"    pm.expect(pm.response.responseTime).to.be.below(200);\r",
											"});"
										],
										"type": "text/javascript"
									}
								}
							],
							"request": {
								"method": "PUT",
								"header": [],
								"body": {
									"mode": "raw",
									"raw": "{\r\n    \"role\":\"Admin\"\r\n}",
									"options": {
										"raw": {
											"language": "json"
										}
									}
								},
								"url": {
									"raw": "{{baseUrl}}/api/user/{{id_user}}/changerole",
									"host": [
										"{{baseUrl}}"
									],
									"path": [
										"api",
										"user",
										"{{id_user}}",
										"changerole"
									]
								}
							},
							"response": [
								{
									"name": "Change User Password Copy",
									"originalRequest": {
										"method": "PUT",
										"header": [],
										"body": {
											"mode": "raw",
											"raw": "{\r\n    \"role\":\"Admin\"\r\n}",
											"options": {
												"raw": {
													"language": "json"
												}
											}
										},
										"url": {
											"raw": "{{baseUrl}}/api/user/{{id_user}}/changerole",
											"host": [
												"{{baseUrl}}"
											],
											"path": [
												"api",
												"user",
												"{{id_user}}",
												"changerole"
											]
										}
									},
									"status": "Unauthorized",
									"code": 401,
									"_postman_previewlanguage": "json",
									"header": [
										{
											"key": "X-Powered-By",
											"value": "Express"
										},
										{
											"key": "Content-Type",
											"value": "application/json; charset=utf-8"
										},
										{
											"key": "Content-Length",
											"value": "71"
										},
										{
											"key": "ETag",
											"value": "W/\"47-aV1Zm6nX06nynHblONUSOM0SuRk\""
										},
										{
											"key": "Date",
											"value": "Wed, 13 Dec 2023 16:17:11 GMT"
										},
										{
											"key": "Connection",
											"value": "keep-alive"
										},
										{
											"key": "Keep-Alive",
											"value": "timeout=5"
										}
									],
									"cookie": [],
									"body": "{\n    \"code\": 401,\n    \"message\": \"You are not authorized to access this resource\"\n}"
								},
								{
									"name": "Change User Password Copy",
									"originalRequest": {
										"method": "PUT",
										"header": [],
										"body": {
											"mode": "raw",
											"raw": "{\r\n    \"role\":\"Admin\"\r\n}",
											"options": {
												"raw": {
													"language": "json"
												}
											}
										},
										"url": {
											"raw": "{{baseUrl}}/api/user/{{id_user}}/changerole",
											"host": [
												"{{baseUrl}}"
											],
											"path": [
												"api",
												"user",
												"{{id_user}}",
												"changerole"
											]
										}
									},
									"status": "OK",
									"code": 200,
									"_postman_previewlanguage": "json",
									"header": [
										{
											"key": "X-Powered-By",
											"value": "Express"
										},
										{
											"key": "Content-Type",
											"value": "application/json; charset=utf-8"
										},
										{
											"key": "Content-Length",
											"value": "237"
										},
										{
											"key": "ETag",
											"value": "W/\"ed-MVlbStU2XQCHwGa9ptDVWnfRcc8\""
										},
										{
											"key": "Date",
											"value": "Wed, 13 Dec 2023 16:20:02 GMT"
										},
										{
											"key": "Connection",
											"value": "keep-alive"
										},
										{
											"key": "Keep-Alive",
											"value": "timeout=5"
										}
									],
									"cookie": [],
									"body": "{\n    \"code\": 200,\n    \"data\": {\n        \"id\": 1,\n        \"name\": \"nishi\",\n        \"email\": \"admin@mail.com\",\n        \"number\": \"232121321\",\n        \"photo_url\": \"\",\n        \"role\": \"Admin\",\n        \"createdAt\": \"2023-12-13T15:11:44.623Z\",\n        \"updatedAt\": \"2023-12-13T15:46:39.130Z\"\n    },\n    \"message\": \"Role User berhasil diupdate\"\n}"
								}
							]
						}
					]
				}
			]
		},
		{
			"name": "services",
			"item": [
				{
					"name": "To get all serives available",
					"event": [
						{
							"listen": "test",
							"script": {
								"exec": [
									"pm.test(\"Status code is 200\", function () {\r",
									"    pm.response.to.have.status(200);\r",
									"});\r",
									"pm.test(\"Response time is less than 200ms\", function () {\r",
									"    pm.expect(pm.response.responseTime).to.be.below(200);\r",
									"});"
								],
								"type": "text/javascript"
							}
						}
					],
					"request": {
						"method": "GET",
						"header": [
							{
								"key": "Accept",
								"value": "application/json"
							}
						],
						"url": {
							"raw": "{{baseUrl}}/api/services",
							"host": [
								"{{baseUrl}}"
							],
							"path": [
								"api",
								"services"
							]
						},
						"description": "To get all serives available"
					},
					"response": [
						{
							"name": "Successfuly get all services data",
							"originalRequest": {
								"method": "GET",
								"header": [
									{
										"key": "Accept",
										"value": "application/json"
									}
								],
								"url": {
									"raw": "{{baseUrl}}/services",
									"host": [
										"{{baseUrl}}"
									],
									"path": [
										"services"
									]
								}
							},
							"status": "OK",
							"code": 200,
							"_postman_previewlanguage": "json",
							"header": [
								{
									"key": "Content-Type",
									"value": "application/json"
								}
							],
							"cookie": [],
							"body": "{\n  \"name\": \"<string>\",\n  \"description\": \"<string>\"\n}"
						},
						{
							"name": "Unauthorized Error",
							"originalRequest": {
								"method": "GET",
								"header": [
									{
										"key": "Accept",
										"value": "application/json"
									}
								],
								"url": {
									"raw": "{{baseUrl}}/services",
									"host": [
										"{{baseUrl}}"
									],
									"path": [
										"services"
									]
								}
							},
							"status": "Unauthorized",
							"code": 401,
							"_postman_previewlanguage": "json",
							"header": [
								{
									"key": "Content-Type",
									"value": "application/json"
								}
							],
							"cookie": [],
							"body": "{\n  \"message\": \"<string>\"\n}"
						},
						{
							"name": "To get all serives available",
							"originalRequest": {
								"method": "GET",
								"header": [
									{
										"key": "Accept",
										"value": "application/json"
									}
								],
								"url": {
									"raw": "{{baseUrl}}/api/services",
									"host": [
										"{{baseUrl}}"
									],
									"path": [
										"api",
										"services"
									]
								}
							},
							"status": "OK",
							"code": 200,
							"_postman_previewlanguage": "json",
							"header": [
								{
									"key": "X-Powered-By",
									"value": "Express"
								},
								{
									"key": "Content-Type",
									"value": "application/json; charset=utf-8"
								},
								{
									"key": "Content-Length",
									"value": "437"
								},
								{
									"key": "ETag",
									"value": "W/\"1b5-pP279pijSWUOrYMg+/iSvglLUsM\""
								},
								{
									"key": "Date",
									"value": "Wed, 13 Dec 2023 17:19:44 GMT"
								},
								{
									"key": "Connection",
									"value": "keep-alive"
								},
								{
									"key": "Keep-Alive",
									"value": "timeout=5"
								}
							],
							"cookie": [],
							"body": "{\n    \"code\": 200,\n    \"data\": [\n        {\n            \"id\": 1,\n            \"serviceName\": \"Haircut\",\n            \"description\": \"A haircut is the style in which hair is cut. Haircuts of medium length are very popular due to their wide variety, which allows you to find the most suitable haircut and create with its help an individual and extraordinary image.\",\n            \"isActive\": false,\n            \"createdAt\": \"2023-12-13T16:55:39.515Z\",\n            \"updatedAt\": \"2023-12-13T16:55:39.515Z\"\n        }\n    ],\n    \"message\": \"Data Service berhasil diambil\"\n}"
						},
						{
							"name": "To get all serives available",
							"originalRequest": {
								"method": "GET",
								"header": [
									{
										"key": "Accept",
										"value": "application/json"
									}
								],
								"url": {
									"raw": "{{baseUrl}}/api/services",
									"host": [
										"{{baseUrl}}"
									],
									"path": [
										"api",
										"services"
									]
								}
							},
							"status": "OK",
							"code": 200,
							"_postman_previewlanguage": "json",
							"header": [
								{
									"key": "X-Powered-By",
									"value": "Express"
								},
								{
									"key": "Content-Type",
									"value": "application/json; charset=utf-8"
								},
								{
									"key": "Content-Length",
									"value": "64"
								},
								{
									"key": "ETag",
									"value": "W/\"40-KwUVGiIRgIAK3ut4USWQc7FrULo\""
								},
								{
									"key": "Date",
									"value": "Wed, 13 Dec 2023 17:26:31 GMT"
								},
								{
									"key": "Connection",
									"value": "keep-alive"
								},
								{
									"key": "Keep-Alive",
									"value": "timeout=5"
								}
							],
							"cookie": [],
							"body": "{\n    \"code\": 200,\n    \"data\": [],\n    \"message\": \"Data Service berhasil diambil\"\n}"
						}
					]
				},
				{
					"name": "To create service",
					"event": [
						{
							"listen": "test",
							"script": {
								"exec": [
									"pm.test(\"Status code is 201\", function () {\r",
									"    pm.response.to.have.status(201);\r",
									"});\r",
									"pm.test(\"Response time is less than 200ms\", function () {\r",
									"    pm.expect(pm.response.responseTime).to.be.below(200);\r",
									"});\r",
									"pm.collectionVariables.set(\"serviceId\", pm.response.json().data.id);"
								],
								"type": "text/javascript"
							}
						}
					],
					"request": {
						"method": "POST",
						"header": [],
						"body": {
							"mode": "raw",
							"raw": "{\r\n    \"serviceName\" : \"{{$randomProductName}}\",\r\n    \"description\":\"{{$randomProductAdjective}}\"\r\n}",
							"options": {
								"raw": {
									"language": "json"
								}
							}
						},
						"url": {
							"raw": "{{baseUrl}}/api/services",
							"host": [
								"{{baseUrl}}"
							],
							"path": [
								"api",
								"services"
							]
						}
					},
					"response": [
						{
							"name": "New Request",
							"originalRequest": {
								"method": "POST",
								"header": [],
								"body": {
									"mode": "raw",
									"raw": "{\r\n    \"serviceName\" : \"Krimbat\",\r\n    \"description\":\"Wash hair with luxury\"\r\n}",
									"options": {
										"raw": {
											"language": "json"
										}
									}
								},
								"url": {
									"raw": "{{baseUrl}}/api/services",
									"host": [
										"{{baseUrl}}"
									],
									"path": [
										"api",
										"services"
									]
								}
							},
							"status": "Unauthorized",
							"code": 401,
							"_postman_previewlanguage": "json",
							"header": [
								{
									"key": "X-Powered-By",
									"value": "Express"
								},
								{
									"key": "Content-Type",
									"value": "application/json; charset=utf-8"
								},
								{
									"key": "Content-Length",
									"value": "50"
								},
								{
									"key": "ETag",
									"value": "W/\"32-Cjdo8gev6Z/UfjXt8+pTuyGK5eE\""
								},
								{
									"key": "Date",
									"value": "Wed, 13 Dec 2023 19:19:24 GMT"
								},
								{
									"key": "Connection",
									"value": "keep-alive"
								},
								{
									"key": "Keep-Alive",
									"value": "timeout=5"
								}
							],
							"cookie": [],
							"body": "{\n    \"code\": 401,\n    \"message\": \"Anda tidak memiliki akses\"\n}"
						},
						{
							"name": "New Request",
							"originalRequest": {
								"method": "POST",
								"header": [],
								"body": {
									"mode": "raw",
									"raw": "{\r\n    \"serviceName\" : \"Krimbat\",\r\n    \"description\":\"Wash hair with luxury\"\r\n}",
									"options": {
										"raw": {
											"language": "json"
										}
									}
								},
								"url": {
									"raw": "{{baseUrl}}/api/services",
									"host": [
										"{{baseUrl}}"
									],
									"path": [
										"api",
										"services"
									]
								}
							},
							"status": "Created",
							"code": 201,
							"_postman_previewlanguage": "json",
							"header": [
								{
									"key": "X-Powered-By",
									"value": "Express"
								},
								{
									"key": "Content-Type",
									"value": "application/json; charset=utf-8"
								},
								{
									"key": "Content-Length",
									"value": "230"
								},
								{
									"key": "ETag",
									"value": "W/\"e6-987ISPgmrnAo7XRdUW5kbBNqkaU\""
								},
								{
									"key": "Date",
									"value": "Wed, 13 Dec 2023 19:29:54 GMT"
								},
								{
									"key": "Connection",
									"value": "keep-alive"
								},
								{
									"key": "Keep-Alive",
									"value": "timeout=5"
								}
							],
							"cookie": [],
							"body": "{\n    \"code\": 201,\n    \"data\": {\n        \"isActive\": true,\n        \"id\": 6,\n        \"serviceName\": \"Krimbat\",\n        \"description\": \"Wash hair with luxury\",\n        \"updatedAt\": \"2023-12-13T19:29:54.453Z\",\n        \"createdAt\": \"2023-12-13T19:29:54.453Z\"\n    },\n    \"message\": \"Data Service berhasil ditambahkan\"\n}"
						}
					]
				},
				{
					"name": "To update the service",
					"event": [
						{
							"listen": "test",
							"script": {
								"exec": [
									"pm.test(\"Status code is 200\", function () {\r",
									"    pm.response.to.have.status(200);\r",
									"});\r",
									"pm.test(\"Response time is less than 200ms\", function () {\r",
									"    pm.expect(pm.response.responseTime).to.be.below(200);\r",
									"});"
								],
								"type": "text/javascript"
							}
						}
					],
					"request": {
						"method": "PUT",
						"header": [],
						"body": {
							"mode": "raw",
							"raw": "{\r\n    \"serviceName\" : \"Krimbat Edited\",\r\n    \"description\":\"Wash hair with luxury and many more\"\r\n}",
							"options": {
								"raw": {
									"language": "json"
								}
							}
						},
						"url": {
							"raw": "{{baseUrl}}/api/services/{{serviceId}}",
							"host": [
								"{{baseUrl}}"
							],
							"path": [
								"api",
								"services",
								"{{serviceId}}"
							]
						}
					},
					"response": [
						{
							"name": "To update the service",
							"originalRequest": {
								"method": "PUT",
								"header": [],
								"body": {
									"mode": "raw",
									"raw": "{\r\n    \"serviceName\" : \"Krimbat Edited\",\r\n    \"description\":\"Wash hair with luxury and many more\"\r\n}",
									"options": {
										"raw": {
											"language": "json"
										}
									}
								},
								"url": {
									"raw": "{{baseUrl}}/api/services/{{serviceId}}",
									"host": [
										"{{baseUrl}}"
									],
									"path": [
										"api",
										"services",
										"{{serviceId}}"
									]
								}
							},
							"status": "OK",
							"code": 200,
							"_postman_previewlanguage": "json",
							"header": [
								{
									"key": "X-Powered-By",
									"value": "Express"
								},
								{
									"key": "Content-Type",
									"value": "application/json; charset=utf-8"
								},
								{
									"key": "Content-Length",
									"value": "147"
								},
								{
									"key": "ETag",
									"value": "W/\"93-gcFl7WZVJ+Zrd2JytsDMnvkGN0M\""
								},
								{
									"key": "Date",
									"value": "Wed, 13 Dec 2023 19:42:40 GMT"
								},
								{
									"key": "Connection",
									"value": "keep-alive"
								},
								{
									"key": "Keep-Alive",
									"value": "timeout=5"
								}
							],
							"cookie": [],
							"body": "{\n    \"code\": 200,\n    \"data\": {\n        \"serviceName\": \"Krimbat Edited\",\n        \"description\": \"Wash hair with luxury and many more\"\n    },\n    \"message\": \"Data Service berhasil diupdate\"\n}"
						}
					]
				}
			]
		},
		{
			"name": "kapster",
			"item": [
				{
					"name": "Create new Kapster",
					"event": [
						{
							"listen": "test",
							"script": {
								"exec": [
									"pm.test(\"Response time is less than 200ms\", function () {\r",
									"    pm.expect(pm.response.responseTime).to.be.below(200);\r",
									"});\r",
									"pm.test(\"Successful POST request\", function () {\r",
									"    pm.expect(pm.response.code).to.be.oneOf([201, 202]);\r",
									"});\r",
									"pm.collectionVariables.set(\"kapsterId\", pm.response.json().data.id);"
								],
								"type": "text/javascript"
							}
						}
					],
					"request": {
						"method": "POST",
						"header": [],
						"body": {
							"mode": "raw",
							"raw": "{\r\n    \"name\" : \"Dian\",\r\n    \"gender\" : \"Woman\",\r\n    \"specialization\":\"Krimbat\",\r\n    \"status\" : \"Available\"\r\n}",
							"options": {
								"raw": {
									"language": "json"
								}
							}
						},
						"url": {
							"raw": "{{baseUrl}}/api/kapsters/",
							"host": [
								"{{baseUrl}}"
							],
							"path": [
								"api",
								"kapsters",
								""
							]
						}
					},
					"response": []
				},
				{
					"name": "Api to get all barberman infomation and its service",
					"event": [
						{
							"listen": "test",
							"script": {
								"exec": [
									"pm.test(\"Status code is 200\", function () {\r",
									"    pm.response.to.have.status(200);\r",
									"});\r",
									"pm.test(\"Response time is less than 200ms\", function () {\r",
									"    pm.expect(pm.response.responseTime).to.be.below(200);\r",
									"});"
								],
								"type": "text/javascript"
							}
						}
					],
					"request": {
						"method": "GET",
						"header": [
							{
								"key": "Accept",
								"value": "application/json"
							}
						],
						"url": {
							"raw": "{{baseUrl}}/api/kapsters",
							"host": [
								"{{baseUrl}}"
							],
							"path": [
								"api",
								"kapsters"
							]
						},
						"description": "Api to get all barberman infomation and its service"
					},
					"response": [
						{
							"name": "Successfuly get all services data",
							"originalRequest": {
								"method": "GET",
								"header": [
									{
										"key": "Accept",
										"value": "application/json"
									}
								],
								"url": {
									"raw": "{{baseUrl}}/barberman?specialization=<string>",
									"host": [
										"{{baseUrl}}"
									],
									"path": [
										"barberman"
									],
									"query": [
										{
											"key": "specialization",
											"value": "<string>"
										}
									]
								}
							},
							"status": "OK",
							"code": 200,
							"_postman_previewlanguage": "json",
							"header": [
								{
									"key": "Content-Type",
									"value": "application/json"
								}
							],
							"cookie": [],
							"body": "[\n  {\n    \"barberman\": {\n      \"id\": \"<integer>\",\n      \"name\": \"<string>\",\n      \"specialization\": \"<string>\"\n    },\n    \"services\": [\n      {\n        \"serviceId\": \"<integer>\",\n        \"price\": \"<integer>\"\n      },\n      {\n        \"serviceId\": \"<integer>\",\n        \"price\": \"<integer>\"\n      }\n    ]\n  },\n  {\n    \"barberman\": {\n      \"id\": \"<integer>\",\n      \"name\": \"<string>\",\n      \"specialization\": \"<string>\"\n    },\n    \"services\": [\n      {\n        \"serviceId\": \"<integer>\",\n        \"price\": \"<integer>\"\n      },\n      {\n        \"serviceId\": \"<integer>\",\n        \"price\": \"<integer>\"\n      }\n    ]\n  }\n]"
						},
						{
							"name": "Unauthorized Error",
							"originalRequest": {
								"method": "GET",
								"header": [
									{
										"key": "Accept",
										"value": "application/json"
									}
								],
								"url": {
									"raw": "{{baseUrl}}/barberman?specialization=<string>",
									"host": [
										"{{baseUrl}}"
									],
									"path": [
										"barberman"
									],
									"query": [
										{
											"key": "specialization",
											"value": "<string>"
										}
									]
								}
							},
							"status": "Unauthorized",
							"code": 401,
							"_postman_previewlanguage": "json",
							"header": [
								{
									"key": "Content-Type",
									"value": "application/json"
								}
							],
							"cookie": [],
							"body": "{\n  \"message\": \"<string>\"\n}"
						},
						{
							"name": "Api to get all barberman infomation and its service",
							"originalRequest": {
								"method": "GET",
								"header": [
									{
										"key": "Accept",
										"value": "application/json"
									}
								],
								"url": {
									"raw": "{{baseUrl}}/api/kapsters",
									"host": [
										"{{baseUrl}}"
									],
									"path": [
										"api",
										"kapsters"
									]
								}
							},
							"status": "OK",
							"code": 200,
							"_postman_previewlanguage": "json",
							"header": [
								{
									"key": "X-Powered-By",
									"value": "Express"
								},
								{
									"key": "Content-Type",
									"value": "application/json; charset=utf-8"
								},
								{
									"key": "Content-Length",
									"value": "394"
								},
								{
									"key": "ETag",
									"value": "W/\"18a-YVqq4ZtmLCnHEK9AEh87I2XvDcM\""
								},
								{
									"key": "Date",
									"value": "Wed, 13 Dec 2023 19:55:48 GMT"
								},
								{
									"key": "Connection",
									"value": "keep-alive"
								},
								{
									"key": "Keep-Alive",
									"value": "timeout=5"
								}
							],
							"cookie": [],
							"body": "{\n    \"code\": 200,\n    \"data\": [\n        {\n            \"id\": 1,\n            \"name\": \"Erwin\",\n            \"gender\": \"Man\",\n            \"specialization\": \"Haircut\",\n            \"status\": \"Available\",\n            \"createdAt\": \"2023-12-13T16:57:46.825Z\",\n            \"updatedAt\": \"2023-12-13T16:57:46.825Z\"\n        },\n        {\n            \"id\": 3,\n            \"name\": \"Erwin\",\n            \"gender\": \"Man\",\n            \"specialization\": \"Haircut\",\n            \"status\": \"Available\",\n            \"createdAt\": \"2023-12-13T16:59:01.697Z\",\n            \"updatedAt\": \"2023-12-13T16:59:01.697Z\"\n        }\n    ],\n    \"message\": \"Data Kapster berhasil diambil.\"\n}"
						}
					]
				},
				{
					"name": "Get Kapster Services",
					"event": [
						{
							"listen": "test",
							"script": {
								"exec": [
									"pm.test(\"Status code is 200\", function () {\r",
									"    pm.response.to.have.status(200);\r",
									"});\r",
									"pm.test(\"Response time is less than 200ms\", function () {\r",
									"    pm.expect(pm.response.responseTime).to.be.below(200);\r",
									"});"
								],
								"type": "text/javascript"
							}
						}
					],
					"request": {
						"method": "GET",
						"header": [],
						"url": {
							"raw": "{{baseUrl}}/api/kapsters/{{kapsterId}}",
							"host": [
								"{{baseUrl}}"
							],
							"path": [
								"api",
								"kapsters",
								"{{kapsterId}}"
							]
						}
					},
					"response": []
				},
				{
					"name": "Update kapster",
					"event": [
						{
							"listen": "test",
							"script": {
								"exec": [
									"pm.test(\"Response time is less than 200ms\", function () {\r",
									"    pm.expect(pm.response.responseTime).to.be.below(200);\r",
									"});\r",
									"pm.test(\"Successful 200 request\", function () {\r",
									"    pm.expect(pm.response.code).to.equal(200);\r",
									"});"
								],
								"type": "text/javascript"
							}
						}
					],
					"request": {
						"method": "PUT",
						"header": [],
						"body": {
							"mode": "raw",
							"raw": "{\r\n    \"name\" : \"Dian Updated\",\r\n    \"gender\" : \"Woman\",\r\n    \"specialization\":\"Krimbat Manalagi\",\r\n    \"status\" : \"Resigned\"\r\n}",
							"options": {
								"raw": {
									"language": "json"
								}
							}
						},
						"url": {
							"raw": "{{baseUrl}}/api/kapsters/{{kapsterId}}",
							"host": [
								"{{baseUrl}}"
							],
							"path": [
								"api",
								"kapsters",
								"{{kapsterId}}"
							]
						}
					},
					"response": [
						{
							"name": "Update kapster",
							"originalRequest": {
								"method": "PUT",
								"header": [],
								"body": {
									"mode": "raw",
									"raw": "{\r\n    \"name\" : \"Dian Updated\",\r\n    \"gender\" : \"Woman\",\r\n    \"specialization\":\"Krimbat Manalagi\",\r\n    \"status\" : \"Resigned\"\r\n}",
									"options": {
										"raw": {
											"language": "json"
										}
									}
								},
								"url": {
									"raw": "{{baseUrl}}/api/kapsters/{{kapsterId}}",
									"host": [
										"{{baseUrl}}"
									],
									"path": [
										"api",
										"kapsters",
										"{{kapsterId}}"
									]
								}
							},
							"status": "OK",
							"code": 200,
							"_postman_previewlanguage": "json",
							"header": [
								{
									"key": "X-Powered-By",
									"value": "Express"
								},
								{
									"key": "Content-Type",
									"value": "application/json; charset=utf-8"
								},
								{
									"key": "Content-Length",
									"value": "167"
								},
								{
									"key": "ETag",
									"value": "W/\"a7-QEky04FtvPVJzQFT5RT4ll4Kj4s\""
								},
								{
									"key": "Date",
									"value": "Wed, 13 Dec 2023 20:56:17 GMT"
								},
								{
									"key": "Connection",
									"value": "keep-alive"
								},
								{
									"key": "Keep-Alive",
									"value": "timeout=5"
								}
							],
							"cookie": [],
							"body": "{\n    \"code\": 200,\n    \"data\": {\n        \"id\": \"7\",\n        \"name\": \"Dian Updated\",\n        \"gender\": \"Woman\",\n        \"specialization\": \"Krimbat Manalagi\",\n        \"status\": \"Resigned\"\n    },\n    \"message\": \"Kapster successfully updated.\"\n}"
						}
					]
				}
			]
		},
		{
			"name": "service kapster",
			"item": [
				{
					"name": "{id}",
					"item": [
						{
							"name": "Update Kapster Service (price, isActive)",
							"event": [
								{
									"listen": "test",
									"script": {
										"exec": [
											"pm.test(\"Status code is 200\", function () {\r",
											"    pm.response.to.have.status(200);\r",
											"});\r",
											"pm.test(\"Response time is less than 200ms\", function () {\r",
											"    pm.expect(pm.response.responseTime).to.be.below(200);\r",
											"});"
										],
										"type": "text/javascript"
									}
								}
							],
							"request": {
								"method": "PUT",
								"header": [],
								"body": {
									"mode": "raw",
									"raw": "{\r\n    \"isActive\": {{$randomBoolean}},\r\n    \"price\": {{$randomPrice}}\r\n}",
									"options": {
										"raw": {
											"language": "json"
										}
									}
								},
								"url": {
									"raw": "{{baseUrl}}/api/kapster-service/{{kapsterServiceId}}",
									"host": [
										"{{baseUrl}}"
									],
									"path": [
										"api",
										"kapster-service",
										"{{kapsterServiceId}}"
									]
								}
							},
							"response": [
								{
									"name": "Update Kapster Service (price, isActive)",
									"originalRequest": {
										"method": "PUT",
										"header": [],
										"body": {
											"mode": "raw",
											"raw": "{\r\n    \"isActive\": {{$randomBoolean}},\r\n    \"price\": {{$randomPrice}}\r\n}",
											"options": {
												"raw": {
													"language": "json"
												}
											}
										},
										"url": {
											"raw": "{{baseUrl}}/api/kapster-service/{{kapsterServiceId}}",
											"host": [
												"{{baseUrl}}"
											],
											"path": [
												"api",
												"kapster-service",
												"{{kapsterServiceId}}"
											]
										}
									},
									"status": "OK",
									"code": 200,
									"_postman_previewlanguage": "json",
									"header": [
										{
											"key": "X-Powered-By",
											"value": "Express"
										},
										{
											"key": "Content-Type",
											"value": "application/json; charset=utf-8"
										},
										{
											"key": "Content-Length",
											"value": "198"
										},
										{
											"key": "ETag",
											"value": "W/\"c6-gpecBNSJHsPrOeKOZA3B679oqE0\""
										},
										{
											"key": "Date",
											"value": "Thu, 14 Dec 2023 10:33:59 GMT"
										},
										{
											"key": "Connection",
											"value": "keep-alive"
										},
										{
											"key": "Keep-Alive",
											"value": "timeout=5"
										}
									],
									"cookie": [],
									"body": "{\n    \"code\": 200,\n    \"data\": {\n        \"id\": 3,\n        \"kapsterId\": 2,\n        \"serviceId\": 2,\n        \"isActive\": true,\n        \"price\": 291,\n        \"createdAt\": \"2023-12-14T10:15:32.679Z\",\n        \"updatedAt\": \"2023-12-14T10:33:59.830Z\"\n    },\n    \"message\": \"Kapster service updated\"\n}"
								}
							]
						}
					]
				},
				{
					"name": "Create New Kapster Service",
					"event": [
						{
							"listen": "test",
							"script": {
								"exec": [
									"pm.collectionVariables.set(\"kapsterServiceId\", pm.response.json().data.id);\r",
									"pm.test(\"Response time is less than 200ms\", function () {\r",
									"    pm.expect(pm.response.responseTime).to.be.below(200);\r",
									"});\r",
									"pm.test(\"Successful POST request\", function () {\r",
									"    pm.expect(pm.response.code).to.be.oneOf([201, 202]);\r",
									"});"
								],
								"type": "text/javascript"
							}
						}
					],
					"request": {
						"method": "POST",
						"header": [],
						"body": {
							"mode": "raw",
							"raw": "{\r\n   \"kapsterId\" : {{kapsterId}},\r\n   \"serviceId\" : {{serviceId}},\r\n   \"price\": 100000\r\n}",
							"options": {
								"raw": {
									"language": "json"
								}
							}
						},
						"url": {
							"raw": "{{baseUrl}}/api/kapster-service",
							"host": [
								"{{baseUrl}}"
							],
							"path": [
								"api",
								"kapster-service"
							]
						}
					},
					"response": []
				}
			]
		},
		{
			"name": "appointment",
			"item": [
				{
					"name": "{id}",
					"item": [
						{
							"name": "Get appointment",
							"event": [
								{
									"listen": "test",
									"script": {
										"exec": [
											"pm.test(\"Status code is 200\", function () {\r",
											"    pm.response.to.have.status(200);\r",
											"});\r",
											"pm.test(\"Response time is less than 200ms\", function () {\r",
											"    pm.expect(pm.response.responseTime).to.be.below(200);\r",
											"});"
										],
										"type": "text/javascript"
									}
								}
							],
							"request": {
								"method": "GET",
								"header": [
									{
										"key": "Accept",
										"value": "application/json"
									}
								],
								"url": {
									"raw": "{{baseUrl}}/api/appointment/{{appointmentId}}",
									"host": [
										"{{baseUrl}}"
									],
									"path": [
										"api",
										"appointment",
										"{{appointmentId}}"
									]
								},
								"description": "Get appointment"
							},
							"response": [
								{
									"name": "Get appointment according id",
									"originalRequest": {
										"method": "GET",
										"header": [
											{
												"key": "Accept",
												"value": "application/json"
											}
										],
										"url": {
											"raw": "{{baseUrl}}/appointment/:id",
											"host": [
												"{{baseUrl}}"
											],
											"path": [
												"appointment",
												":id"
											],
											"variable": [
												{
													"key": "id"
												}
											]
										}
									},
									"status": "OK",
									"code": 200,
									"_postman_previewlanguage": "json",
									"header": [
										{
											"key": "Content-Type",
											"value": "application/json"
										}
									],
									"cookie": [],
									"body": "{\n  \"id\": \"<integer>\",\n  \"user\": {\n    \"id\": \"<number>\",\n    \"name\": \"<string>\",\n    \"passwod\": \"<string>\",\n    \"email\": \"<string>\",\n    \"number\": \"<string>\",\n    \"photo_url\": \"<string>\"\n  },\n  \"service\": {\n    \"name\": \"<string>\",\n    \"description\": \"<string>\"\n  },\n  \"barberman\": {\n    \"id\": \"<integer>\",\n    \"name\": \"<string>\",\n    \"specialization\": \"<string>\"\n  },\n  \"date\": \"<number>\",\n  \"status\": \"<string>\",\n  \"time\": \"<integer>\"\n}"
								},
								{
									"name": "Unauthorized Error",
									"originalRequest": {
										"method": "GET",
										"header": [
											{
												"key": "Accept",
												"value": "application/json"
											}
										],
										"url": {
											"raw": "{{baseUrl}}/appointment/:id",
											"host": [
												"{{baseUrl}}"
											],
											"path": [
												"appointment",
												":id"
											],
											"variable": [
												{
													"key": "id"
												}
											]
										}
									},
									"status": "Unauthorized",
									"code": 401,
									"_postman_previewlanguage": "json",
									"header": [
										{
											"key": "Content-Type",
											"value": "application/json"
										}
									],
									"cookie": [],
									"body": "{\n  \"message\": \"<string>\"\n}"
								},
								{
									"name": "Not permitted error",
									"originalRequest": {
										"method": "GET",
										"header": [
											{
												"key": "Accept",
												"value": "application/json"
											}
										],
										"url": {
											"raw": "{{baseUrl}}/appointment/:id",
											"host": [
												"{{baseUrl}}"
											],
											"path": [
												"appointment",
												":id"
											],
											"variable": [
												{
													"key": "id"
												}
											]
										}
									},
									"status": "Forbidden",
									"code": 403,
									"_postman_previewlanguage": "json",
									"header": [
										{
											"key": "Content-Type",
											"value": "application/json"
										}
									],
									"cookie": [],
									"body": "{\n  \"message\": \"<string>\"\n}"
								},
								{
									"name": "Not Found Error",
									"originalRequest": {
										"method": "GET",
										"header": [
											{
												"key": "Accept",
												"value": "application/json"
											}
										],
										"url": {
											"raw": "{{baseUrl}}/appointment/:id",
											"host": [
												"{{baseUrl}}"
											],
											"path": [
												"appointment",
												":id"
											],
											"variable": [
												{
													"key": "id"
												}
											]
										}
									},
									"status": "Not Found",
									"code": 404,
									"_postman_previewlanguage": "json",
									"header": [
										{
											"key": "Content-Type",
											"value": "application/json"
										}
									],
									"cookie": [],
									"body": "{\n  \"message\": \"<string>\"\n}"
								}
							]
						},
						{
							"name": "Update appointment",
							"event": [
								{
									"listen": "test",
									"script": {
										"exec": [
											"pm.test(\"Status code is 200\", function () {\r",
											"    pm.response.to.have.status(200);\r",
											"});\r",
											"pm.test(\"Response time is less than 200ms\", function () {\r",
											"    pm.expect(pm.response.responseTime).to.be.below(200);\r",
											"});"
										],
										"type": "text/javascript"
									}
								}
							],
							"request": {
								"method": "PUT",
								"header": [
									{
										"key": "Content-Type",
										"value": "application/json"
									},
									{
										"key": "Accept",
										"value": "application/json"
									}
								],
								"body": {
									"mode": "raw",
									"raw": "{\n \"status\": \"Completed\",\n \"time\" :\"{{$randomDateFuture}}\"\n}",
									"options": {
										"raw": {
											"headerFamily": "json",
											"language": "json"
										}
									}
								},
								"url": {
									"raw": "{{baseUrl}}/api/appointment/{{appointmentId}}",
									"host": [
										"{{baseUrl}}"
									],
									"path": [
										"api",
										"appointment",
										"{{appointmentId}}"
									]
								},
								"description": "Update appointment"
							},
							"response": [
								{
									"name": "update appointment",
									"originalRequest": {
										"method": "PUT",
										"header": [
											{
												"key": "Content-Type",
												"value": "application/json"
											},
											{
												"key": "Accept",
												"value": "application/json"
											}
										],
										"body": {
											"mode": "raw",
											"raw": "{\n  \"userId\": \"<integer>\",\n  \"serviceId\": \"<integer>\",\n  \"barbermanId\": \"<integer>\",\n  \"date\": \"<number>\",\n  \"status\": \"<string>\",\n  \"time\": \"<integer>\"\n}",
											"options": {
												"raw": {
													"headerFamily": "json",
													"language": "json"
												}
											}
										},
										"url": {
											"raw": "{{baseUrl}}/appointment/:id",
											"host": [
												"{{baseUrl}}"
											],
											"path": [
												"appointment",
												":id"
											],
											"variable": [
												{
													"key": "id"
												}
											]
										}
									},
									"status": "OK",
									"code": 200,
									"_postman_previewlanguage": "json",
									"header": [
										{
											"key": "Content-Type",
											"value": "application/json"
										}
									],
									"cookie": [],
									"body": "{\n  \"id\": \"<integer>\",\n  \"user\": {\n    \"id\": \"<number>\",\n    \"name\": \"<string>\",\n    \"passwod\": \"<string>\",\n    \"email\": \"<string>\",\n    \"number\": \"<string>\",\n    \"photo_url\": \"<string>\"\n  },\n  \"service\": {\n    \"name\": \"<string>\",\n    \"description\": \"<string>\"\n  },\n  \"barberman\": {\n    \"id\": \"<integer>\",\n    \"name\": \"<string>\",\n    \"specialization\": \"<string>\"\n  },\n  \"date\": \"<number>\",\n  \"status\": \"<string>\",\n  \"time\": \"<integer>\"\n}"
								},
								{
									"name": "Unauthorized Error",
									"originalRequest": {
										"method": "PUT",
										"header": [
											{
												"key": "Content-Type",
												"value": "application/json"
											},
											{
												"key": "Accept",
												"value": "application/json"
											}
										],
										"body": {
											"mode": "raw",
											"raw": "{\n  \"userId\": \"<integer>\",\n  \"serviceId\": \"<integer>\",\n  \"barbermanId\": \"<integer>\",\n  \"date\": \"<number>\",\n  \"status\": \"<string>\",\n  \"time\": \"<integer>\"\n}",
											"options": {
												"raw": {
													"headerFamily": "json",
													"language": "json"
												}
											}
										},
										"url": {
											"raw": "{{baseUrl}}/appointment/:id",
											"host": [
												"{{baseUrl}}"
											],
											"path": [
												"appointment",
												":id"
											],
											"variable": [
												{
													"key": "id"
												}
											]
										}
									},
									"status": "Unauthorized",
									"code": 401,
									"_postman_previewlanguage": "json",
									"header": [
										{
											"key": "Content-Type",
											"value": "application/json"
										}
									],
									"cookie": [],
									"body": "{\n  \"message\": \"<string>\"\n}"
								},
								{
									"name": "Not permitted error",
									"originalRequest": {
										"method": "PUT",
										"header": [
											{
												"key": "Content-Type",
												"value": "application/json"
											},
											{
												"key": "Accept",
												"value": "application/json"
											}
										],
										"body": {
											"mode": "raw",
											"raw": "{\n  \"userId\": \"<integer>\",\n  \"serviceId\": \"<integer>\",\n  \"barbermanId\": \"<integer>\",\n  \"date\": \"<number>\",\n  \"status\": \"<string>\",\n  \"time\": \"<integer>\"\n}",
											"options": {
												"raw": {
													"headerFamily": "json",
													"language": "json"
												}
											}
										},
										"url": {
											"raw": "{{baseUrl}}/appointment/:id",
											"host": [
												"{{baseUrl}}"
											],
											"path": [
												"appointment",
												":id"
											],
											"variable": [
												{
													"key": "id"
												}
											]
										}
									},
									"status": "Forbidden",
									"code": 403,
									"_postman_previewlanguage": "json",
									"header": [
										{
											"key": "Content-Type",
											"value": "application/json"
										}
									],
									"cookie": [],
									"body": "{\n  \"message\": \"<string>\"\n}"
								}
							]
						}
					]
				},
				{
					"name": "Create New Appointment",
					"event": [
						{
							"listen": "test",
							"script": {
								"exec": [
									"pm.collectionVariables.set(\"appointmentId\", pm.response.json().data.id);\r",
									"pm.test(\"Response time is less than 200ms\", function () {\r",
									"    pm.expect(pm.response.responseTime).to.be.below(200);\r",
									"});\r",
									"pm.test(\"Successful POST request\", function () {\r",
									"    pm.expect(pm.response.code).to.be.oneOf([201, 202]);\r",
									"});"
								],
								"type": "text/javascript"
							}
						}
					],
					"request": {
						"method": "POST",
						"header": [
							{
								"key": "Content-Type",
								"value": "application/json"
							},
							{
								"key": "Accept",
								"value": "application/json"
							}
						],
						"body": {
							"mode": "raw",
							"raw": "{\n    \"serviceId\": {{serviceId}},\n    \"kapsterId\": {{kapsterId}},\n    \"time\": \"{{$randomDateFuture}}\"\n}",
							"options": {
								"raw": {
									"headerFamily": "json",
									"language": "json"
								}
							}
						},
						"url": {
							"raw": "{{baseUrl}}/api/appointment",
							"host": [
								"{{baseUrl}}"
							],
							"path": [
								"api",
								"appointment"
							]
						},
						"description": "To post new appointment"
					},
					"response": [
						{
							"name": "To post new appointment",
							"originalRequest": {
								"method": "POST",
								"header": [
									{
										"key": "Content-Type",
										"value": "application/json"
									},
									{
										"key": "Accept",
										"value": "application/json"
									}
								],
								"body": {
									"mode": "raw",
									"raw": "{\n    \"serviceId\": {{serviceId}},\n    \"kapsterId\": {{kapsterId}},\n    \"time\": \"{{$randomDateFuture}}\"\n}",
									"options": {
										"raw": {
											"headerFamily": "json",
											"language": "json"
										}
									}
								},
								"url": {
									"raw": "{{baseUrl}}/api/appointment",
									"host": [
										"{{baseUrl}}"
									],
									"path": [
										"api",
										"appointment"
									]
								}
							},
							"status": "Created",
							"code": 201,
							"_postman_previewlanguage": "json",
							"header": [
								{
									"key": "X-Powered-By",
									"value": "Express"
								},
								{
									"key": "Content-Type",
									"value": "application/json; charset=utf-8"
								},
								{
									"key": "Content-Length",
									"value": "286"
								},
								{
									"key": "ETag",
									"value": "W/\"11e-JAXnCuQO4m4bZHnO2XCqphHkooE\""
								},
								{
									"key": "Date",
									"value": "Thu, 14 Dec 2023 10:55:22 GMT"
								},
								{
									"key": "Connection",
									"value": "keep-alive"
								},
								{
									"key": "Keep-Alive",
									"value": "timeout=5"
								}
							],
							"cookie": [],
							"body": "{\n    \"code\": 201,\n    \"data\": {\n        \"serviceId\": 2,\n        \"kapsterId\": 2,\n        \"time\": \"2024-10-28T18:43:45.000Z\",\n        \"userId\": 4,\n        \"status\": \"Booked\",\n        \"date\": \"2023-12-14T10:55:22.160Z\",\n        \"id\": \"APT00000000001\",\n        \"updatedAt\": \"2023-12-14T10:55:22.165Z\",\n        \"createdAt\": \"2023-12-14T10:55:22.165Z\"\n    },\n    \"message\": \"Appointment berhasil dibuat\"\n}"
						}
					]
				},
				{
					"name": "Get all appointment (admin)",
					"event": [
						{
							"listen": "test",
							"script": {
								"exec": [
									"pm.test(\"Status code is 200\", function () {\r",
									"    pm.response.to.have.status(200);\r",
									"});\r",
									"pm.test(\"Response time is less than 200ms\", function () {\r",
									"    pm.expect(pm.response.responseTime).to.be.below(200);\r",
									"});"
								],
								"type": "text/javascript"
							}
						}
					],
					"request": {
						"method": "GET",
						"header": [],
						"url": {
							"raw": "{{baseUrl}}/api/appointment",
							"host": [
								"{{baseUrl}}"
							],
							"path": [
								"api",
								"appointment"
							]
						}
					},
					"response": [
						{
							"name": "New Request",
							"originalRequest": {
								"method": "GET",
								"header": [],
								"url": {
									"raw": "{{baseUrl}}/api/appointment",
									"host": [
										"{{baseUrl}}"
									],
									"path": [
										"api",
										"appointment"
									]
								}
							},
							"status": "Unauthorized",
							"code": 401,
							"_postman_previewlanguage": "json",
							"header": [
								{
									"key": "X-Powered-By",
									"value": "Express"
								},
								{
									"key": "Content-Type",
									"value": "application/json; charset=utf-8"
								},
								{
									"key": "Content-Length",
									"value": "76"
								},
								{
									"key": "ETag",
									"value": "W/\"4c-swMF+bOMmS3SZ2nxnmYDTnZXGNI\""
								},
								{
									"key": "Date",
									"value": "Thu, 14 Dec 2023 11:18:37 GMT"
								},
								{
									"key": "Connection",
									"value": "keep-alive"
								},
								{
									"key": "Keep-Alive",
									"value": "timeout=5"
								}
							],
							"cookie": [],
							"body": "{\n    \"code\": 401,\n    \"message\": \"Anda tidak memiliki akses untuk melihat appointment\"\n}"
						}
					]
				}
			]
		}
	],
	"event": [
		{
			"listen": "prerequest",
			"script": {
				"type": "text/javascript",
				"exec": [
					""
				]
			}
		},
		{
			"listen": "test",
			"script": {
				"type": "text/javascript",
				"exec": [
					""
				]
			}
		}
	],
	"variable": [
		{
			"key": "baseUrl",
			"value": "http://127.0.0.1:3000"
		},
		{
			"key": "email",
			"value": "customer@mail.com",
			"type": "string"
		},
		{
			"key": "name",
			"value": "vocasia",
			"type": "string"
		},
		{
			"key": "number",
			"value": "08122222222",
			"type": "string"
		},
		{
			"key": "password",
			"value": "12345678",
			"type": "string"
		},
		{
			"key": "photo_url",
			"value": "",
			"type": "string"
		},
		{
			"key": "token_customer",
			"value": "",
			"type": "string"
		},
		{
			"key": "role",
			"value": "",
			"type": "string"
		},
		{
			"key": "admin_email",
			"value": "admin@mail.com",
			"type": "string"
		},
		{
			"key": "admin_password",
			"value": "12345678",
			"type": "string"
		},
		{
			"key": "id_user",
			"value": "1",
			"type": "string"
		},
		{
			"key": "serviceId",
			"value": "",
			"type": "string"
		},
		{
			"key": "kapsterId",
			"value": "1",
			"type": "string"
		},
		{
			"key": "kapsterServiceId",
			"value": "",
			"type": "string"
		},
		{
			"key": "appointmentId",
			"value": "",
			"type": "string"
		},
		{
			"key": "token_admin",
			"value": ""
		}
	]
}